hbdatacache/__init__.py
hbdatacache-0.5.dist-info/METADATA
hbdatacache-0.5.dist-info/WHEEL
hbdatacache-0.5.dist-info/top_level.txt
hbdatacache-0.5.dist-info/RECORD
