Metadata-Version: 2.1
Name: hbdatacache
Version: 0.5
Summary: Package to manage temporary files in the cache and streamline codes with downloads and repetitive functions
Home-page: https://github.com/ZehLuckmann/hbdatacache
Author: José Henrique Luckmann
Author-email: joseh.luckmann@gmail.com
License: UNKNOWN
Platform: UNKNOWN
Classifier: Programming Language :: Python :: 3
Classifier: License :: OSI Approved :: MIT License
Classifier: Operating System :: OS Independent
